CHANGES.txt
MANIFEST.in
README.rst
setup.py
django_muckraking.egg-info/PKG-INFO
django_muckraking.egg-info/SOURCES.txt
django_muckraking.egg-info/dependency_links.txt
django_muckraking.egg-info/requires.txt
django_muckraking.egg-info/top_level.txt
muckraking/__init__.py
muckraking/context_processors/__init__.py
muckraking/management/__init__.py
muckraking/management/commands/__init__.py
muckraking/management/commands/import_redirects.py
muckraking/middleware/__init__.py
muckraking/template/__init__.py
muckraking/template/context_processors.py
muckraking/templatetags/__init__.py
muckraking/templatetags/muckraking_cms_tags.py
muckraking/templatetags/muckraking_tags.py