Metadata-Version: 1.0
Name: django-muckraking
Version: 0.3
Summary: A collection of random Django utilities
Home-page: https://github.com/ryanbagwell/django-muckraking
Author: Ryan Bagwell
Author-email: ryan@ryanbagwell.com
License: Creative Commons Attribution-Noncommercial-Share Alike license
Platform: UNKNOWN
